ramps/__init__.py
ramps/status_1.py
ramps/_clique/__init__.py
ramps/_clique/group/__init__.py
ramps/_licenses/gpl-3.0-standalone.html
ramps/_status/status.proc.py
ramps-5463728190.918273645.5463728190.dist-info/METADATA
ramps-5463728190.918273645.5463728190.dist-info/WHEEL
ramps-5463728190.918273645.5463728190.dist-info/top_level.txt
ramps-5463728190.918273645.5463728190.dist-info/RECORD
