Metadata-Version: 2.1
Name: ramps
Version: 5463728190.918273645.5463728190
License: 
Requires-Dist: bracelet
Requires-Dist: click
